{"cat":"batman","name":"Batman","emoji":"🦇","questions":[{"q":"¿Cuál es el nombre real de Enigma (Riddler)?","o":["Waylon Jones","Edward Nigma","Victor Fries","Basil Karlo"],"c":1,"e":"🎭"},{"q":"¿Qué qué personaje se llama en realidad Edward Nigma?","o":["Enigma (Riddler)","Killer Croc","Dos Caras","Gatúbela"],"c":0,"e":"🎭"},{"q":"¿Cuál es el nombre real de El Pingüino?","o":["Oswald Cobblepot","Jonathan Crane","Basil Karlo","Thomas Elliot"],"c":0,"e":"🎭"},{"q":"¿Qué qué personaje se llama en realidad Oswald Cobblepot?","o":["Hombre Murciélago (Man-Bat)","Calendar Man","Harley Quinn","El Pingüino"],"c":3,"e":"🎭"},{"q":"¿Cuál es el nombre real de Dos Caras?","o":["Victor Zsasz","Thomas Elliot","Kirk Langstrom","Harvey Dent"],"c":3,"e":"🎭"},{"q":"¿Qué qué personaje se llama en realidad Harvey Dent?","o":["Dos Caras","Hush","Enigma (Riddler)","Hiedra Venenosa"],"c":0,"e":"🎭"},{"q":"¿Cuál es el nombre real de Gatúbela?","o":["Julian Day","Selina Kyle","Edward Nigma","Victor Zsasz"],"c":1,"e":"🎭"},{"q":"¿Qué qué personaje se llama en realidad Selina Kyle?","o":["Hiedra Venenosa","Espantapájaros","Gatúbela","Killer Croc"],"c":2,"e":"🎭"},{"q":"¿Cuál es el nombre real de Hiedra Venenosa?","o":["Floyd Lawton","Garfield Lynns","Pamela Isley","Julian Day"],"c":2,"e":"🎭"},{"q":"¿Qué qué personaje se llama en realidad Pamela Isley?","o":["Hiedra Venenosa","Cara de Barro","Gatúbela","Mr. Frío"],"c":0,"e":"🎭"},{"q":"¿Cuál es el nombre real de Mr. Frío?","o":["Roman Sionis","Waylon Jones","Victor Fries","Basil Karlo"],"c":2,"e":"🎭"},{"q":"¿Qué qué personaje se llama en realidad Victor Fries?","o":["Mr. Zsasz","Mr. Frío","Calendar Man","Firefly"],"c":1,"e":"🎭"},{"q":"¿Cuál es el nombre real de Espantapájaros?","o":["Thomas Elliot","Jonathan Crane","Jervis Tetch","Victor Fries"],"c":1,"e":"🎭"},{"q":"¿Qué qué personaje se llama en realidad Jonathan Crane?","o":["Gatúbela","Espantapájaros","Cara de Barro","Hush"],"c":1,"e":"🎭"},{"q":"¿Cuál es el nombre real de Harley Quinn?","o":["Edward Nigma","Oswald Cobblepot","Harleen Quinzel","Thomas Elliot"],"c":2,"e":"🎭"},{"q":"¿Qué qué personaje se llama en realidad Harleen Quinzel?","o":["Hiedra Venenosa","Harley Quinn","El Sombrerero Loco","Cara de Barro"],"c":1,"e":"🎭"},{"q":"¿Cuál es el nombre real de Killer Croc?","o":["Jervis Tetch","Oswald Cobblepot","Waylon Jones","Julian Day"],"c":2,"e":"🎭"},{"q":"¿Qué qué personaje se llama en realidad Waylon Jones?","o":["Enigma (Riddler)","Espantapájaros","Dos Caras","Killer Croc"],"c":3,"e":"🎭"},{"q":"¿Cuál es el nombre real de Cara de Barro?","o":["Basil Karlo","Garfield Lynns","Roman Sionis","Edward Nigma"],"c":0,"e":"🎭"},{"q":"¿Qué qué personaje se llama en realidad Basil Karlo?","o":["Hombre Murciélago (Man-Bat)","Calendar Man","Cara de Barro","Harley Quinn"],"c":2,"e":"🎭"},{"q":"¿Cuál es el nombre real de El Sombrerero Loco?","o":["Jervis Tetch","Harvey Dent","Roman Sionis","Floyd Lawton"],"c":0,"e":"🎭"},{"q":"¿Qué qué personaje se llama en realidad Jervis Tetch?","o":["El Sombrerero Loco","Deadshot","Enigma (Riddler)","Harley Quinn"],"c":0,"e":"🎭"},{"q":"¿Cuál es el nombre real de Hombre Murciélago (Man-Bat)?","o":["Kirk Langstrom","Garfield Lynns","Waylon Jones","Victor Zsasz"],"c":0,"e":"🎭"},{"q":"¿Qué qué personaje se llama en realidad Kirk Langstrom?","o":["Deadshot","Calendar Man","Hombre Murciélago (Man-Bat)","Cara de Barro"],"c":2,"e":"🎭"},{"q":"¿Cuál es el nombre real de Deadshot?","o":["Pamela Isley","Floyd Lawton","Selina Kyle","Waylon Jones"],"c":1,"e":"🎭"},{"q":"¿Qué qué personaje se llama en realidad Floyd Lawton?","o":["Mr. Frío","Dos Caras","Deadshot","Máscara Negra"],"c":2,"e":"🎭"},{"q":"¿Cuál es el nombre real de Máscara Negra?","o":["Edward Nigma","Harvey Dent","Roman Sionis","Victor Fries"],"c":2,"e":"🎭"},{"q":"¿Qué qué personaje se llama en realidad Roman Sionis?","o":["Espantapájaros","Deadshot","Dos Caras","Máscara Negra"],"c":3,"e":"🎭"},{"q":"¿Cuál es el nombre real de Firefly?","o":["Garfield Lynns","Oswald Cobblepot","Kirk Langstrom","Edward Nigma"],"c":0,"e":"🎭"},{"q":"¿Qué qué personaje se llama en realidad Garfield Lynns?","o":["Firefly","Enigma (Riddler)","Gatúbela","Deadshot"],"c":0,"e":"🎭"},{"q":"¿Cuál es el nombre real de Hush?","o":["Garfield Lynns","Harvey Dent","Victor Zsasz","Thomas Elliot"],"c":3,"e":"🎭"},{"q":"¿Qué qué personaje se llama en realidad Thomas Elliot?","o":["Hombre Murciélago (Man-Bat)","Hush","El Pingüino","Deadshot"],"c":1,"e":"🎭"},{"q":"¿Cuál es el nombre real de Mr. Zsasz?","o":["Floyd Lawton","Thomas Elliot","Victor Zsasz","Jonathan Crane"],"c":2,"e":"🎭"},{"q":"¿Qué qué personaje se llama en realidad Victor Zsasz?","o":["Mr. Zsasz","Hombre Murciélago (Man-Bat)","Killer Croc","Hiedra Venenosa"],"c":0,"e":"🎭"},{"q":"¿Cuál es el nombre real de Calendar Man?","o":["Julian Day","Harleen Quinzel","Basil Karlo","Victor Fries"],"c":0,"e":"🎭"},{"q":"¿Qué qué personaje se llama en realidad Julian Day?","o":["Calendar Man","Máscara Negra","Gatúbela","Hush"],"c":0,"e":"🎭"},{"q":"¿Cuál es el nombre real de Batman?","o":["Barbara Gordon","Jason Todd","Bruce Wayne","Damian Wayne"],"c":2,"e":"🦸"},{"q":"¿Qué qué personaje se llama en realidad Bruce Wayne?","o":["Nightwing","Batman","el primer Robin","Oráculo (Oracle)"],"c":1,"e":"🦸"},{"q":"¿Cuál es el nombre real de el primer Robin?","o":["Jason Todd","Dick Grayson","Bruce Wayne","Kate Kane"],"c":1,"e":"🦸"},{"q":"¿Qué qué personaje se llama en realidad Dick Grayson?","o":["el primer Robin","el tercer Robin","Nightwing","Red Hood (moderno)"],"c":0,"e":"🦸"},{"q":"¿Cuál es el nombre real de el segundo Robin?","o":["Tim Drake","Bruce Wayne","Damian Wayne","Jason Todd"],"c":3,"e":"🦸"},{"q":"¿Qué qué personaje se llama en realidad Jason Todd?","o":["Red Hood (moderno)","Batwoman","el segundo Robin","el tercer Robin"],"c":2,"e":"🦸"},{"q":"¿Cuál es el nombre real de el tercer Robin?","o":["Barbara Gordon","Kate Kane","Jason Todd","Tim Drake"],"c":3,"e":"🦸"},{"q":"¿Qué qué personaje se llama en realidad Tim Drake?","o":["Nightwing","el tercer Robin","Batwoman","el Robin hijo de Bruce"],"c":1,"e":"🦸"},{"q":"¿Cuál es el nombre real de el Robin hijo de Bruce?","o":["Barbara Gordon","Bruce Wayne","Dick Grayson","Damian Wayne"],"c":3,"e":"🦸"},{"q":"¿Qué qué personaje se llama en realidad Damian Wayne?","o":["el tercer Robin","el Robin hijo de Bruce","Batwoman","Nightwing"],"c":1,"e":"🦸"},{"q":"¿Cuál es el nombre real de Batgirl?","o":["Barbara Gordon","Kate Kane","Dick Grayson","Damian Wayne"],"c":0,"e":"🦸"},{"q":"¿Qué qué personaje se llama en realidad Barbara Gordon?","o":["el segundo Robin","el tercer Robin","Batgirl","Red Hood (moderno)"],"c":2,"e":"🦸"},{"q":"¿Cuál es el nombre real de Nightwing?","o":["Tim Drake","Barbara Gordon","Kate Kane","Dick Grayson"],"c":3,"e":"🦸"},{"q":"¿Cuál es el nombre real de Red Hood (moderno)?","o":["Bruce Wayne","Damian Wayne","Jason Todd","Dick Grayson"],"c":2,"e":"🦸"},{"q":"¿Cuál es el nombre real de Batwoman?","o":["Tim Drake","Kate Kane","Damian Wayne","Dick Grayson"],"c":1,"e":"🦸"},{"q":"¿Qué qué personaje se llama en realidad Kate Kane?","o":["Oráculo (Oracle)","el tercer Robin","el segundo Robin","Batwoman"],"c":3,"e":"🦸"},{"q":"¿Cuál es el nombre real de Oráculo (Oracle)?","o":["Kate Kane","Damian Wayne","Barbara Gordon","Dick Grayson"],"c":2,"e":"🦸"},{"q":"¿Quién interpretó Batman en 'Batman' (1989) y 'Batman Returns'?","o":["Colin Farrell","Michelle Pfeiffer","Michael Keaton","Joaquin Phoenix"],"c":2,"e":"🎬"},{"q":"¿A qué papel a qué papel interpretó Michael Keaton?","o":["Batman en la trilogía de Christopher Nolan","al Enigma en 'Batman Forever'","al Enigma en 'The Batman' (2022)","Batman en 'Batman' (1989) y 'Batman Returns'"],"c":3,"e":"🎬"},{"q":"¿Quién interpretó Batman en 'Batman Forever' (1995)?","o":["Cillian Murphy","Colin Farrell","Val Kilmer","Aaron Eckhart"],"c":2,"e":"🎬"},{"q":"¿A qué papel a qué papel interpretó Val Kilmer?","o":["Batman en 'Batman y Robin' (1997)","al Enigma en 'Batman Forever'","a Gatúbela en 'The Batman' (2022)","Batman en 'Batman Forever' (1995)"],"c":3,"e":"🎬"},{"q":"¿Quién interpretó Batman en 'Batman y Robin' (1997)?","o":["George Clooney","Colin Farrell","Arnold Schwarzenegger","Jack Nicholson"],"c":0,"e":"🎬"},{"q":"¿A qué papel a qué papel interpretó George Clooney?","o":["al Enigma en 'Batman Forever'","a Mr. Frío en 'Batman y Robin'","al Joker en 'Batman' (1989)","Batman en 'Batman y Robin' (1997)"],"c":3,"e":"🎬"},{"q":"¿Quién interpretó Batman en la trilogía de Christopher Nolan?","o":["Uma Thurman","Christian Bale","George Clooney","Aaron Eckhart"],"c":1,"e":"🎬"},{"q":"¿A qué papel a qué papel interpretó Christian Bale?","o":["Batman en la serie clásica de los años 60","Batman en la trilogía de Christopher Nolan","Batman en 'The Batman' (2022)","a Ra's al Ghul en 'Batman Begins'"],"c":1,"e":"🎬"},{"q":"¿Quién interpretó Batman en 'Batman v Superman' (2016)?","o":["Heath Ledger","Danny DeVito","Ben Affleck","Joaquin Phoenix"],"c":2,"e":"🎬"},{"q":"¿A qué papel a qué papel interpretó Ben Affleck?","o":["al Joker en 'Joker' (2019)","Batman en 'Batman v Superman' (2016)","a Mr. Frío en 'Batman y Robin'","al Pingüino en 'The Batman' (2022)"],"c":1,"e":"🎬"},{"q":"¿Quién interpretó Batman en 'The Batman' (2022)?","o":["Robert Pattinson","Jack Nicholson","Val Kilmer","Uma Thurman"],"c":0,"e":"🎬"},{"q":"¿A qué papel a qué papel interpretó Robert Pattinson?","o":["Batman en la trilogía de Christopher Nolan","a Mr. Frío en 'Batman y Robin'","al Enigma en 'Batman Forever'","Batman en 'The Batman' (2022)"],"c":3,"e":"🎬"},{"q":"¿Quién interpretó Batman en la serie clásica de los años 60?","o":["Tom Hardy","Adam West","Val Kilmer","Michael Keaton"],"c":1,"e":"🎬"},{"q":"¿A qué papel a qué papel interpretó Adam West?","o":["al Pingüino en 'Batman Returns'","Batman en 'Batman v Superman' (2016)","a Mr. Frío en 'Batman y Robin'","Batman en la serie clásica de los años 60"],"c":3,"e":"🎬"},{"q":"¿Quién interpretó al Joker en 'Batman' (1989)?","o":["Arnold Schwarzenegger","Jack Nicholson","Cillian Murphy","Zoë Kravitz"],"c":1,"e":"🎬"},{"q":"¿A qué papel a qué papel interpretó Jack Nicholson?","o":["al Espantapájaros en 'Batman Begins'","Batman en 'The Batman' (2022)","a Gatúbela en 'Batman Returns'","al Joker en 'Batman' (1989)"],"c":3,"e":"🎬"},{"q":"¿Quién interpretó al Joker en 'The Dark Knight' (2008)?","o":["Heath Ledger","Adam West","Jim Carrey","Paul Dano"],"c":0,"e":"🎬"},{"q":"¿A qué papel a qué papel interpretó Heath Ledger?","o":["a Hiedra Venenosa en 'Batman y Robin'","a Gatúbela en 'Batman Returns'","a Bane en 'The Dark Knight Rises'","al Joker en 'The Dark Knight' (2008)"],"c":3,"e":"🎬"},{"q":"¿Quién interpretó al Joker en 'Joker' (2019)?","o":["Arnold Schwarzenegger","Liam Neeson","Danny DeVito","Joaquin Phoenix"],"c":3,"e":"🎬"},{"q":"¿A qué papel a qué papel interpretó Joaquin Phoenix?","o":["Batman en la serie clásica de los años 60","al Joker en 'Joker' (2019)","al Espantapájaros en 'Batman Begins'","Batman en 'Batman y Robin' (1997)"],"c":1,"e":"🎬"},{"q":"¿Quién interpretó a Bane en 'The Dark Knight Rises'?","o":["Ben Affleck","Cillian Murphy","Tom Hardy","George Clooney"],"c":2,"e":"🎬"},{"q":"¿A qué papel a qué papel interpretó Tom Hardy?","o":["Batman en la trilogía de Christopher Nolan","a Bane en 'The Dark Knight Rises'","al Pingüino en 'Batman Returns'","al Enigma en 'The Batman' (2022)"],"c":1,"e":"🎬"},{"q":"¿Quién interpretó al Enigma en 'The Batman' (2022)?","o":["Heath Ledger","Paul Dano","Christian Bale","Michael Keaton"],"c":1,"e":"🎬"},{"q":"¿A qué papel a qué papel interpretó Paul Dano?","o":["al Enigma en 'The Batman' (2022)","a Ra's al Ghul en 'Batman Begins'","al Joker en 'The Dark Knight' (2008)","Batman en 'Batman Forever' (1995)"],"c":0,"e":"🎬"},{"q":"¿Quién interpretó al Pingüino en 'The Batman' (2022)?","o":["George Clooney","Tom Hardy","Jack Nicholson","Colin Farrell"],"c":3,"e":"🎬"},{"q":"¿A qué papel a qué papel interpretó Colin Farrell?","o":["Batman en 'Batman y Robin' (1997)","Batman en la trilogía de Christopher Nolan","al Pingüino en 'The Batman' (2022)","Batman en 'Batman Forever' (1995)"],"c":2,"e":"🎬"},{"q":"¿Quién interpretó a Gatúbela en 'Batman Returns'?","o":["Ben Affleck","Jim Carrey","Michelle Pfeiffer","Liam Neeson"],"c":2,"e":"🎬"},{"q":"¿A qué papel a qué papel interpretó Michelle Pfeiffer?","o":["a Gatúbela en 'The Batman' (2022)","a Gatúbela en 'Batman Returns'","Batman en la trilogía de Christopher Nolan","al Joker en 'The Dark Knight' (2008)"],"c":1,"e":"🎬"},{"q":"¿Quién interpretó a Gatúbela en 'The Batman' (2022)?","o":["Liam Neeson","Zoë Kravitz","Heath Ledger","Aaron Eckhart"],"c":1,"e":"🎬"},{"q":"¿A qué papel a qué papel interpretó Zoë Kravitz?","o":["al Enigma en 'The Batman' (2022)","a Gatúbela en 'The Batman' (2022)","al Pingüino en 'The Batman' (2022)","a Mr. Frío en 'Batman y Robin'"],"c":1,"e":"🎬"},{"q":"¿Quién interpretó a Ra's al Ghul en 'Batman Begins'?","o":["Michelle Pfeiffer","Liam Neeson","Robert Pattinson","Michael Keaton"],"c":1,"e":"🎬"},{"q":"¿A qué papel a qué papel interpretó Liam Neeson?","o":["a Ra's al Ghul en 'Batman Begins'","a Mr. Frío en 'Batman y Robin'","Batman en 'Batman y Robin' (1997)","Batman en 'Batman' (1989) y 'Batman Returns'"],"c":0,"e":"🎬"},{"q":"¿Quién interpretó al Espantapájaros en 'Batman Begins'?","o":["Cillian Murphy","Adam West","Jim Carrey","Colin Farrell"],"c":0,"e":"🎬"},{"q":"¿A qué papel a qué papel interpretó Cillian Murphy?","o":["al Enigma en 'Batman Forever'","al Espantapájaros en 'Batman Begins'","Batman en 'Batman v Superman' (2016)","al Joker en 'The Dark Knight' (2008)"],"c":1,"e":"🎬"},{"q":"¿Quién interpretó a Harvey Dent en 'The Dark Knight'?","o":["Uma Thurman","Adam West","Cillian Murphy","Aaron Eckhart"],"c":3,"e":"🎬"},{"q":"¿A qué papel a qué papel interpretó Aaron Eckhart?","o":["a Ra's al Ghul en 'Batman Begins'","a Gatúbela en 'The Batman' (2022)","a Harvey Dent en 'The Dark Knight'","al Joker en 'Joker' (2019)"],"c":2,"e":"🎬"},{"q":"¿Quién interpretó a Mr. Frío en 'Batman y Robin'?","o":["Arnold Schwarzenegger","Ben Affleck","Tom Hardy","Zoë Kravitz"],"c":0,"e":"🎬"},{"q":"¿A qué papel a qué papel interpretó Arnold Schwarzenegger?","o":["Batman en la serie clásica de los años 60","Batman en la trilogía de Christopher Nolan","al Enigma en 'The Batman' (2022)","a Mr. Frío en 'Batman y Robin'"],"c":3,"e":"🎬"},{"q":"¿Quién interpretó a Hiedra Venenosa en 'Batman y Robin'?","o":["Danny DeVito","George Clooney","Uma Thurman","Jack Nicholson"],"c":2,"e":"🎬"},{"q":"¿A qué papel a qué papel interpretó Uma Thurman?","o":["Batman en 'Batman' (1989) y 'Batman Returns'","al Pingüino en 'Batman Returns'","a Hiedra Venenosa en 'Batman y Robin'","al Espantapájaros en 'Batman Begins'"],"c":2,"e":"🎬"},{"q":"¿Quién interpretó al Enigma en 'Batman Forever'?","o":["Aaron Eckhart","Jim Carrey","Michelle Pfeiffer","Robert Pattinson"],"c":1,"e":"🎬"},{"q":"¿A qué papel a qué papel interpretó Jim Carrey?","o":["al Enigma en 'Batman Forever'","a Gatúbela en 'The Batman' (2022)","Batman en 'The Batman' (2022)","Batman en la serie clásica de los años 60"],"c":0,"e":"🎬"},{"q":"¿Quién interpretó al Pingüino en 'Batman Returns'?","o":["Liam Neeson","Val Kilmer","Tom Hardy","Danny DeVito"],"c":3,"e":"🎬"},{"q":"¿A qué papel a qué papel interpretó Danny DeVito?","o":["Batman en 'Batman Forever' (1995)","al Pingüino en 'Batman Returns'","al Enigma en 'Batman Forever'","a Bane en 'The Dark Knight Rises'"],"c":1,"e":"🎬"},{"q":"¿En qué año se estrenó \"Batman\"?","o":["2005","2023","1997","1989"],"c":3,"e":"📅"},{"q":"¿Quién dirigió \"Batman\"?","o":["Joel Schumacher","Christopher Nolan","Tim Burton","Zack Snyder"],"c":2,"e":"🎬"},{"q":"¿Quién es el villano principal de \"Batman\"?","o":["el Pingüino","el Enigma","el Joker","Dos Caras"],"c":2,"e":"😈"},{"q":"¿Qué película de Batman se estrenó en 1989?","o":["The Batman","The Dark Knight","The Dark Knight Rises","Batman"],"c":3,"e":"🎞️"},{"q":"¿En qué año se estrenó \"Batman Returns\"?","o":["2021","1995","2008","1992"],"c":3,"e":"📅"},{"q":"¿Quién dirigió \"Batman Returns\"?","o":["Zack Snyder","Joel Schumacher","Tim Burton","Matt Reeves"],"c":2,"e":"🎬"},{"q":"¿Quién es el villano principal de \"Batman Returns\"?","o":["el Joker","Ra's al Ghul","el Pingüino","Dos Caras"],"c":2,"e":"😈"},{"q":"¿Qué película de Batman se estrenó en 1992?","o":["Batman","Batman Forever","Batman Returns","The Dark Knight Rises"],"c":2,"e":"🎞️"},{"q":"¿En qué año se estrenó \"Batman Forever\"?","o":["1966","1992","1995","2016"],"c":2,"e":"📅"},{"q":"¿Quién dirigió \"Batman Forever\"?","o":["Christopher Nolan","Joel Schumacher","Zack Snyder","Tim Burton"],"c":1,"e":"🎬"},{"q":"¿Quién es el villano principal de \"Batman Forever\"?","o":["el Joker","Mr. Frío","Bane","el Enigma"],"c":3,"e":"😈"},{"q":"¿Qué película de Batman se estrenó en 1995?","o":["Batman Forever","Batman Returns","The Batman","Batman y Robin"],"c":0,"e":"🎞️"},{"q":"¿En qué año se estrenó \"Batman y Robin\"?","o":["2011","2004","1997","2021"],"c":2,"e":"📅"},{"q":"¿Quién dirigió \"Batman y Robin\"?","o":["Matt Reeves","Joel Schumacher","Tim Burton","Zack Snyder"],"c":1,"e":"🎬"},{"q":"¿Quién es el villano principal de \"Batman y Robin\"?","o":["Lex Luthor","Mr. Frío","el Enigma","el Pingüino"],"c":1,"e":"😈"},{"q":"¿Qué película de Batman se estrenó en 1997?","o":["The Dark Knight Rises","Batman","Batman Begins","Batman y Robin"],"c":3,"e":"🎞️"},{"q":"¿En qué año se estrenó \"Batman Begins\"?","o":["2005","2023","1995","1997"],"c":0,"e":"📅"},{"q":"¿Quién dirigió \"Batman Begins\"?","o":["Zack Snyder","Christopher Nolan","Joel Schumacher","Tim Burton"],"c":1,"e":"🎬"},{"q":"¿Quién es el villano principal de \"Batman Begins\"?","o":["el Enigma","Lex Luthor","Ra's al Ghul","Mr. Frío"],"c":2,"e":"😈"},{"q":"¿Qué película de Batman se estrenó en 2005?","o":["The Dark Knight Rises","Batman Begins","Batman","The Batman"],"c":1,"e":"🎞️"},{"q":"¿En qué año se estrenó \"The Dark Knight\"?","o":["1989","2008","1995","1966"],"c":1,"e":"📅"},{"q":"¿Quién dirigió \"The Dark Knight\"?","o":["Tim Burton","Matt Reeves","Zack Snyder","Christopher Nolan"],"c":3,"e":"🎬"},{"q":"¿Quién es el villano principal de \"The Dark Knight\"?","o":["el Enigma","el Joker","Dos Caras","el Pingüino"],"c":1,"e":"😈"},{"q":"¿Qué película de Batman se estrenó en 2008?","o":["The Batman","The Dark Knight","The Dark Knight Rises","Batman"],"c":1,"e":"🎞️"},{"q":"¿En qué año se estrenó \"The Dark Knight Rises\"?","o":["2005","2022","2012","1995"],"c":2,"e":"📅"},{"q":"¿Quién dirigió \"The Dark Knight Rises\"?","o":["Joel Schumacher","Christopher Nolan","Matt Reeves","Tim Burton"],"c":1,"e":"🎬"},{"q":"¿Quién es el villano principal de \"The Dark Knight Rises\"?","o":["Dos Caras","Bane","Lex Luthor","el Enigma"],"c":1,"e":"😈"},{"q":"¿Qué película de Batman se estrenó en 2012?","o":["Batman Forever","Batman Returns","The Dark Knight Rises","Batman v Superman"],"c":2,"e":"🎞️"},{"q":"¿En qué año se estrenó \"Batman v Superman\"?","o":["2016","2005","2022","2019"],"c":0,"e":"📅"},{"q":"¿Quién dirigió \"Batman v Superman\"?","o":["Christopher Nolan","Matt Reeves","Tim Burton","Zack Snyder"],"c":3,"e":"🎬"},{"q":"¿Quién es el villano principal de \"Batman v Superman\"?","o":["Dos Caras","Lex Luthor","el Joker","Mr. Frío"],"c":1,"e":"😈"},{"q":"¿Qué película de Batman se estrenó en 2016?","o":["Batman Forever","The Batman","Batman v Superman","Batman Begins"],"c":2,"e":"🎞️"},{"q":"¿En qué año se estrenó \"The Batman\"?","o":["2022","1993","2016","2008"],"c":0,"e":"📅"},{"q":"¿Quién dirigió \"The Batman\"?","o":["Christopher Nolan","Matt Reeves","Tim Burton","Zack Snyder"],"c":1,"e":"🎬"},{"q":"¿Quién es el villano principal de \"The Batman\"?","o":["Bane","el Enigma","Ra's al Ghul","Lex Luthor"],"c":1,"e":"😈"},{"q":"¿Qué película de Batman se estrenó en 2022?","o":["Batman","The Dark Knight Rises","The Batman","Batman Begins"],"c":2,"e":"🎞️"},{"q":"¿Qué villano de Batman deja acertijos y adivinanzas?","o":["Hombre Murciélago","Bane","El Enigma","Gatúbela"],"c":2,"e":"❓"},{"q":"¿Qué villano de Batman decide todo lanzando una moneda?","o":["Deadshot","Killer Croc","Dos Caras","Gatúbela"],"c":2,"e":"🪙"},{"q":"¿Qué villano usa una pistola congelante y necesita frío para vivir?","o":["Cara de Barro","Máscara Negra","Mr. Frío","Harley Quinn"],"c":2,"e":"❄️"},{"q":"¿Qué villana controla las plantas y usa toxinas?","o":["Deadshot","Hiedra Venenosa","Pingüino","Azrael"],"c":1,"e":"🌿"},{"q":"¿Qué villano usa un gas del miedo (toxina del terror)?","o":["Calendar Man","Deadshot","Killer Croc","El Espantapájaros"],"c":3,"e":"😱"},{"q":"¿Qué villano se potencia con el suero llamado Veneno (Venom)?","o":["Máscara Negra","Dos Caras","Bane","Hiedra Venenosa"],"c":2,"e":"💉"},{"q":"¿Qué villano usa paraguas trucados y le obsesionan las aves?","o":["Enigma","Pingüino","Cara de Barro","El Pingüino"],"c":3,"e":"☂️"},{"q":"¿Qué villano se cura en los Pozos de Lázaro y busca la inmortalidad?","o":["Ra's al Ghul","Zsasz","Sombrerero Loco","Hombre Murciélago"],"c":0,"e":"🕳️"},{"q":"¿Qué villano marca su piel con una cuchillada por cada víctima?","o":["Mr. Zsasz","Gatúbela","Joker","Cara de Barro"],"c":0,"e":"🔪"},{"q":"¿Qué villano puede transformar su cuerpo de arcilla?","o":["Cara de Barro","Gatúbela","Dos Caras","Espantapájaros"],"c":0,"e":"🟤"},{"q":"¿Qué villano usa sombreros para controlar la mente?","o":["Firefly","Espantapájaros","Killer Croc","El Sombrerero Loco"],"c":3,"e":"🎩"},{"q":"¿Qué villano es un tirador infalible que nunca falla un disparo?","o":["Deadshot","Sombrerero Loco","Cara de Barro","Calendar Man"],"c":0,"e":"🎯"},{"q":"¿Qué villano famoso ríe y usa gas de la risa?","o":["Enigma","El Joker","Harley Quinn","Dos Caras"],"c":1,"e":"🤡"},{"q":"¿Qué villano rompió la espalda de Batman en el cómic 'Knightfall'?","o":["Espantapájaros","Hiedra Venenosa","Bane","Sombrerero Loco"],"c":2,"e":"💥"},{"q":"¿Cuál es la ciudad de Batman?","o":["Central City","Star City","Metrópolis","Ciudad Gótica (Gotham)"],"c":3,"e":"🌃"},{"q":"¿Cómo se llama la mansión donde vive Bruce Wayne?","o":["Mansión Wayne","Mansión Cobblepot","Castillo Kane","Torre Stark"],"c":0,"e":"🏰"},{"q":"¿Cómo se llama la base secreta de Batman?","o":["La Baticueva","La Fortaleza","El Búnker","La Atalaya"],"c":0,"e":"🦇"},{"q":"¿Cómo se llama el mayordomo de Bruce Wayne?","o":["Alfred Pennyworth","Jarvis","Lucius Fox","James Gordon"],"c":0,"e":"🤵"},{"q":"¿Qué rango tiene James Gordon en la policía de Gotham?","o":["Comisionado","Sargento","Detective","Alcalde"],"c":0,"e":"👮"},{"q":"¿Cómo se llama el manicomio donde encierran a los villanos de Batman?","o":["Belle Reve","Prisión de Gotham","Prisión Blackgate","Asilo Arkham"],"c":3,"e":"🏚️"},{"q":"¿Cómo se llamaban los padres de Bruce Wayne?","o":["Thomas y Martha","Henry y Marta","Robert y Elena","Jack y Ana"],"c":0,"e":"👪"},{"q":"¿Quién asesinó a los padres de Bruce Wayne?","o":["Falcone","El Joker","Ra's al Ghul","Joe Chill"],"c":3,"e":"🔫"},{"q":"¿En qué callejón mataron a los padres de Bruce Wayne?","o":["La Avenida Gótica","El Muelle Este","La Plaza Wayne","El Callejón del Crimen"],"c":3,"e":"🌃"},{"q":"¿Qué animal cae sobre Bruce de niño e inspira su símbolo?","o":["Arañas","Murciélagos","Lobos","Cuervos"],"c":1,"e":"🦇"},{"q":"¿Qué empresa dirige Bruce Wayne?","o":["Queen Industries","Empresas Wayne","Industrias Stark","LexCorp"],"c":1,"e":"🏢"},{"q":"¿Quién le fabrica el equipo tecnológico a Batman en las películas de Nolan?","o":["Q","Alfred","Lucius Fox","Comisario Gordon"],"c":2,"e":"🛠️"},{"q":"¿Cuál es la regla que Batman jamás rompe?","o":["No trabajar de día","No revelar su identidad","No usar armas de fuego","No matar"],"c":3,"e":"🚫"},{"q":"¿Cómo apodan a Batman por ser un gran detective?","o":["El hombre de acero","El arquero esmeralda","El mejor detective del mundo","El vigilante rojo"],"c":2,"e":"🔎"},{"q":"¿Qué apodo tiene Batman relacionado con la noche?","o":["El Vengador Escarlata","El Señor de la Luz","El Caballero Oscuro","El Guardián Dorado"],"c":2,"e":"🌑"},{"q":"¿Quiénes crearon a Batman?","o":["Stan Lee y Jack Kirby","Jerry Siegel y Joe Shuster","Steve Ditko y Stan Lee","Bob Kane y Bill Finger"],"c":3,"e":"✍️"},{"q":"¿En qué cómic apareció Batman por primera vez (1939)?","o":["Amazing Fantasy #15","Detective Comics #27","Batman #1","Action Comics #1"],"c":1,"e":"📚"},{"q":"¿A qué editorial pertenece Batman?","o":["Dark Horse","Marvel","Image","DC Comics"],"c":3,"e":"🏷️"},{"q":"¿A qué equipo de superhéroes pertenece Batman?","o":["La Liga de la Justicia","Los Vengadores","Los X-Men","Los 4 Fantásticos"],"c":0,"e":"🦸"},{"q":"¿Cómo se llama el vehículo icónico de Batman?","o":["El Tumbler","El Batmóvil","El Batwing","El Batpod"],"c":1,"e":"🚗"},{"q":"¿Qué arma arrojadiza con forma de murciélago usa Batman?","o":["El bumerán","La Batiestrella","El Batarang","El garfio"],"c":2,"e":"🦇"},{"q":"¿Con qué proyectan el símbolo de Batman en el cielo para llamarlo?","o":["Un reflector normal","Una bengala","Un dron","La Batiseñal"],"c":3,"e":"🔦"},{"q":"¿Qué frase dice Batman al presentarse?","o":["'Temedme'","'Yo soy la noche'","'Soy Batman'","'Soy la venganza'"],"c":2,"e":"🦇"},{"q":"En 'The Batman' (2022), ¿qué frase repite el protagonista?","o":["'Soy Batman'","'Soy la noche'","'Yo soy el miedo'","'Soy la venganza'"],"c":3,"e":"🦇"},{"q":"¿Qué superpoder tiene Batman?","o":["Superfuerza","Volar","Visión láser","Ninguno; es humano y usa entrenamiento y tecnología"],"c":3,"e":"💪"},{"q":"¿Quién es el fiel compañero (sidekick) clásico de Batman?","o":["Robin","Bucky","Kid Flash","Speedy"],"c":0,"e":"🐦"},{"q":"¿Qué robot/perro acompaña a veces a Batman en los cómics?","o":["Krypto","Titus","Ace, el Bati-perro","Lockjaw"],"c":2,"e":"🐕"},{"q":"¿De qué color es el traje clásico de Batman?","o":["Verde y negro","Rojo y azul","Blanco y dorado","Gris y negro"],"c":3,"e":"🎨"},{"q":"¿Qué villano fue fiscal de distrito antes de volverse malo?","o":["El Enigma","Dos Caras (Harvey Dent)","Bane","El Pingüino"],"c":1,"e":"⚖️"},{"q":"¿Qué villana era psiquiatra en Arkham antes de amar al Joker?","o":["Hiedra Venenosa","Talia","Harley Quinn","Gatúbela"],"c":2,"e":"💘"},{"q":"¿Quién es la hija de Ra's al Ghul?","o":["Selina Kyle","Barbara Gordon","Kate Kane","Talia al Ghul"],"c":3,"e":"👩"},{"q":"¿Cómo se llama la organización de asesinos de Ra's al Ghul?","o":["La Liga de las Sombras (Asesinos)","Intergang","La Corte de los Búhos","H.I.V.E."],"c":0,"e":"🗡️"},{"q":"¿Qué sociedad secreta controla Gotham en los cómics modernos?","o":["La Corte de los Búhos","La Liga de las Sombras","La Mano","Hydra"],"c":0,"e":"🦉"},{"q":"En el mundo de Batman, ¿qué es el Batmóvil?","o":["el auto de Batman","la moto de Batman","el arma arrojadiza","la luz para llamarlo"],"c":0,"e":"🦇"},{"q":"En el mundo de Batman, ¿qué es el Batwing?","o":["la moto de Batman","el avión/jet de Batman","el auto de Batman","la luz para llamarlo"],"c":1,"e":"🦇"},{"q":"En el mundo de Batman, ¿qué es el Batpod?","o":["la moto de Batman","el arma arrojadiza","el auto de Batman","el avión/jet de Batman"],"c":0,"e":"🦇"},{"q":"En el mundo de Batman, ¿qué es el Batarang?","o":["el auto de Batman","la luz para llamarlo","la base secreta","el arma arrojadiza"],"c":3,"e":"🦇"},{"q":"En el mundo de Batman, ¿qué es la Baticueva?","o":["el avión/jet de Batman","el auto de Batman","la base secreta","la moto de Batman"],"c":2,"e":"🦇"},{"q":"En el mundo de Batman, ¿qué es la Batiseñal?","o":["el avión/jet de Batman","el arma arrojadiza","el auto de Batman","la luz para llamarlo"],"c":3,"e":"🦇"},{"q":"¿Qué símbolo lleva Batman en el pecho?","o":["Un rayo","Una estrella","Un murciélago","Una araña"],"c":2,"e":"🦇"},{"q":"¿A qué hora suele actuar Batman?","o":["Al mediodía","De noche","A cualquier hora del día","Al amanecer"],"c":1,"e":"🌙"},{"q":"¿Qué profesión pública/faceta tiene Bruce Wayne?","o":["Multimillonario empresario y filántropo","Científico pobre","Periodista","Policía"],"c":0,"e":"💰"},{"q":"¿Qué le pasó a Bruce Wayne de niño para desarrollar su miedo a los murciélagos?","o":["Cayó en un pozo/cueva llena de murciélagos","Soñó con ellos","Lo mordió uno","Vio una película"],"c":0,"e":"🕳️"},{"q":"¿Qué motiva a Bruce Wayne a convertirse en Batman?","o":["Fama","Ganar dinero","Poderes mágicos","Vengar y honrar la muerte de sus padres"],"c":3,"e":"🖤"},{"q":"¿Cómo se llama la prisión de máxima seguridad de Gotham (no el manicomio)?","o":["Arkham","Blackgate","Belle Reve","Alcatraz"],"c":1,"e":"⛓️"},{"q":"¿Qué villano fue creado por un accidente con químicos que lo dejaron pálido y con pelo verde?","o":["El Enigma","El Pingüino","El Joker","Dos Caras"],"c":2,"e":"🤡"},{"q":"¿Qué le desfiguró media cara a Harvey Dent?","o":["Fuego","Un disparo","Una explosión de hielo","Ácido"],"c":3,"e":"⚗️"},{"q":"¿Qué apodo recibe el equipo de aliados de Batman?","o":["Los Centinelas","Los Titanes","Los Vengadores","La Bati-familia"],"c":3,"e":"👨‍👩‍👧"},{"q":"¿Quién fue Robin antes de convertirse en Nightwing?","o":["Jason Todd","Tim Drake","Damian Wayne","Dick Grayson"],"c":3,"e":"🐦"},{"q":"¿Qué Robin fue asesinado por el Joker y luego volvió como Red Hood?","o":["Dick Grayson","Damian Wayne","Tim Drake","Jason Todd"],"c":3,"e":"💀"},{"q":"¿Quién es el hijo biológico de Bruce Wayne que se vuelve Robin?","o":["Damian Wayne","Tim Drake","Jason Todd","Dick Grayson"],"c":0,"e":"👦"},{"q":"¿Qué relación tiene a menudo Gatúbela con Batman?","o":["Su jefa","Su hija","Interés amoroso y a veces aliada","Su hermana"],"c":2,"e":"💋"},{"q":"¿En qué estado suele estar la relación de Batman con la policía en sus inicios?","o":["Lo ignoran","Trabaja oficialmente para ellos","Es el jefe de policía","Lo consideran un vigilante fuera de la ley"],"c":3,"e":"🚓"},{"q":"¿Qué gran evento anual de villanos ocurre en 'El largo Halloween'?","o":["Un torneo","Una serie de asesinatos en días festivos","Una fuga masiva","Una boda"],"c":1,"e":"🎃"},{"q":"¿Qué acorazado vehículo usa Batman en la trilogía de Nolan?","o":["El Batimóvil clásico","El Tumbler","Una motocicleta común","El Batwing"],"c":1,"e":"🚙"},{"q":"¿Qué frase dice Alfred sobre por qué caemos?","o":["'El miedo es el enemigo'","'¿Por qué caemos? Para aprender a levantarnos'","'Nunca te rindas'","'Sé el héroe'"],"c":1,"e":"💬"},{"q":"¿Qué dice Alfred sobre algunos hombres y el Joker en 'The Dark Knight'?","o":["'Nadie es un héroe'","'La ciudad está perdida'","'El dinero lo es todo'","'Algunos hombres solo quieren ver arder el mundo'"],"c":3,"e":"🔥"},{"q":"¿Qué célebre frase dice Harvey Dent sobre héroes y villanos?","o":["'La justicia es ciega'","'Mueres siendo un héroe o vives lo suficiente para volverte el villano'","'El bien siempre gana'","'La verdad duele'"],"c":1,"e":"⚖️"},{"q":"¿Qué ciudad vecina y luminosa se suele contrastar con la oscura Gotham?","o":["Metrópolis (la ciudad de Superman)","Coast City","Central City","Star City"],"c":0,"e":"🌆"},{"q":"¿Con quién forma Batman el 'World's Finest' (dúo clásico)?","o":["Con Aquaman","Con Linterna Verde","Con Flash","Con Superman"],"c":3,"e":"🤝"},{"q":"¿Qué material resistente suele componer el traje de Batman en el cine moderno?","o":["Seda","Cuero simple","Oro","Blindaje/kevlar de alta tecnología"],"c":3,"e":"🛡️"},{"q":"¿Qué hace único a Batman entre los grandes superhéroes?","o":["Puede volar","No tiene superpoderes","Es un alienígena","Tiene superfuerza"],"c":1,"e":"🧠"},{"q":"¿Qué serie animada muy aclamada de los 90 definió a muchos villanos de Batman?","o":["'Los Superamigos'","'Batman Beyond' únicamente","'Batman: la serie animada'","'Teen Titans Go'"],"c":2,"e":"📺"},{"q":"¿Qué villana debutó en 'Batman: la serie animada' antes que en los cómics?","o":["Talia","Gatúbela","Harley Quinn","Hiedra Venenosa"],"c":2,"e":"🃏"},{"q":"¿En qué franquicia de cine actuó Michael Keaton?","o":["Spider-Man","Shrek","El Rey León","Batman"],"c":3,"e":"🎬"},{"q":"¿En qué franquicia de cine actuó Val Kilmer?","o":["Batman","Toy Story","Shrek","Los Increíbles"],"c":0,"e":"🎬"},{"q":"¿En qué franquicia de cine actuó George Clooney?","o":["Batman","Los Increíbles","Toy Story","Harry Potter"],"c":0,"e":"🎬"},{"q":"¿En qué franquicia de cine actuó Christian Bale?","o":["Shrek","Los Increíbles","Toy Story","Batman"],"c":3,"e":"🎬"},{"q":"¿En qué franquicia de cine actuó Ben Affleck?","o":["Los Increíbles","Spider-Man","Shrek","Batman"],"c":3,"e":"🎬"},{"q":"¿En qué franquicia de cine actuó Robert Pattinson?","o":["Shrek","Toy Story","Batman","Star Wars"],"c":2,"e":"🎬"},{"q":"¿En qué franquicia de cine actuó Adam West?","o":["Batman","Toy Story","Shrek","Los Increíbles"],"c":0,"e":"🎬"},{"q":"¿En qué franquicia de cine actuó Jack Nicholson?","o":["Shrek","El Rey León","Harry Potter","Batman"],"c":3,"e":"🎬"},{"q":"¿En qué franquicia de cine actuó Heath Ledger?","o":["Spider-Man","Shrek","Batman","Toy Story"],"c":2,"e":"🎬"},{"q":"¿En qué franquicia de cine actuó Joaquin Phoenix?","o":["Shrek","Star Wars","Harry Potter","Batman"],"c":3,"e":"🎬"},{"q":"¿En qué franquicia de cine actuó Tom Hardy?","o":["Spider-Man","Batman","El Rey León","Shrek"],"c":1,"e":"🎬"},{"q":"¿En qué franquicia de cine actuó Paul Dano?","o":["Shrek","Batman","Star Wars","Toy Story"],"c":1,"e":"🎬"},{"q":"¿En qué franquicia de cine actuó Colin Farrell?","o":["Los Increíbles","Batman","Spider-Man","Shrek"],"c":1,"e":"🎬"},{"q":"¿En qué franquicia de cine actuó Michelle Pfeiffer?","o":["Star Wars","Toy Story","Batman","Harry Potter"],"c":2,"e":"🎬"},{"q":"¿En qué franquicia de cine actuó Zoë Kravitz?","o":["Harry Potter","Los Increíbles","Spider-Man","Batman"],"c":3,"e":"🎬"},{"q":"¿En qué franquicia de cine actuó Liam Neeson?","o":["Harry Potter","Los Increíbles","Batman","Toy Story"],"c":2,"e":"🎬"},{"q":"¿En qué franquicia de cine actuó Cillian Murphy?","o":["Toy Story","Shrek","Star Wars","Batman"],"c":3,"e":"🎬"},{"q":"¿En qué franquicia de cine actuó Aaron Eckhart?","o":["Los Increíbles","Harry Potter","Batman","Spider-Man"],"c":2,"e":"🎬"},{"q":"¿En qué franquicia de cine actuó Arnold Schwarzenegger?","o":["El Rey León","Los Increíbles","Star Wars","Batman"],"c":3,"e":"🎬"},{"q":"¿En qué franquicia de cine actuó Uma Thurman?","o":["Shrek","Batman","Harry Potter","Toy Story"],"c":1,"e":"🎬"},{"q":"¿En qué franquicia de cine actuó Jim Carrey?","o":["Los Increíbles","Batman","Toy Story","Star Wars"],"c":1,"e":"🎬"},{"q":"¿En qué franquicia de cine actuó Danny DeVito?","o":["Toy Story","Star Wars","Batman","Harry Potter"],"c":2,"e":"🎬"},{"q":"¿En qué película Batman se enfrenta a el Joker?","o":["Batman","Batman Returns","The Dark Knight","The Dark Knight Rises"],"c":0,"e":"🥊"},{"q":"¿En qué película Batman se enfrenta a el Pingüino?","o":["Batman Returns","The Dark Knight","The Batman","Batman Begins"],"c":0,"e":"🥊"},{"q":"¿En qué película Batman se enfrenta a el Enigma?","o":["Batman Begins","Batman v Superman","Batman Forever","The Dark Knight Rises"],"c":2,"e":"🥊"},{"q":"¿En qué película Batman se enfrenta a Mr. Frío?","o":["The Batman","Batman y Robin","The Dark Knight","Batman Forever"],"c":1,"e":"🥊"},{"q":"¿En qué película Batman se enfrenta a Ra's al Ghul?","o":["Batman v Superman","The Batman","Batman Begins","Batman"],"c":2,"e":"🥊"},{"q":"¿En qué película Batman se enfrenta a Bane?","o":["The Dark Knight","Batman Returns","The Dark Knight Rises","The Batman"],"c":2,"e":"🥊"},{"q":"¿En qué película Batman se enfrenta a Lex Luthor?","o":["The Dark Knight Rises","Batman Forever","Batman v Superman","Batman y Robin"],"c":2,"e":"🥊"},{"q":"¿En qué película o saga aparece Batman (Bruce Wayne)?","o":["Batman","Los Increíbles","El Rey León","Harry Potter"],"c":0,"e":"🎬"},{"q":"¿A qué franquicia pertenece el personaje Batman (Bruce Wayne)?","o":["Harry Potter","Star Wars","El Rey León","Batman"],"c":3,"e":"🎭"},{"q":"En Batman, ¿Batman (Bruce Wayne) es un héroe/aliado o un villano?","o":["Es un lugar, no un personaje","No aparece en esa saga","Un héroe o aliado","Un villano"],"c":2,"e":"⚖️"},{"q":"¿En qué película o saga aparece Robin (Dick Grayson)?","o":["Shrek","Batman","Toy Story","Los Increíbles"],"c":1,"e":"🎬"},{"q":"¿A qué franquicia pertenece el personaje Robin (Dick Grayson)?","o":["Los Increíbles","Batman","Star Wars","Shrek"],"c":1,"e":"🎭"},{"q":"En Batman, ¿Robin (Dick Grayson) es un héroe/aliado o un villano?","o":["No aparece en esa saga","Es un lugar, no un personaje","Un villano","Un héroe o aliado"],"c":3,"e":"⚖️"},{"q":"¿En qué película o saga aparece Robin (Jason Todd)?","o":["Los Increíbles","Harry Potter","Batman","Toy Story"],"c":2,"e":"🎬"},{"q":"¿A qué franquicia pertenece el personaje Robin (Jason Todd)?","o":["Shrek","Batman","Los Increíbles","Harry Potter"],"c":1,"e":"🎭"},{"q":"En Batman, ¿Robin (Jason Todd) es un héroe/aliado o un villano?","o":["Un villano","Es un lugar, no un personaje","No aparece en esa saga","Un héroe o aliado"],"c":3,"e":"⚖️"},{"q":"¿En qué película o saga aparece Robin (Tim Drake)?","o":["Spider-Man","Harry Potter","Batman","El Rey León"],"c":2,"e":"🎬"},{"q":"¿A qué franquicia pertenece el personaje Robin (Tim Drake)?","o":["Star Wars","Harry Potter","Toy Story","Batman"],"c":3,"e":"🎭"},{"q":"En Batman, ¿Robin (Tim Drake) es un héroe/aliado o un villano?","o":["Un héroe o aliado","Un villano","Es un lugar, no un personaje","No aparece en esa saga"],"c":0,"e":"⚖️"},{"q":"¿En qué película o saga aparece Robin (Damian Wayne)?","o":["Batman","El Rey León","Spider-Man","Los Increíbles"],"c":0,"e":"🎬"},{"q":"¿A qué franquicia pertenece el personaje Robin (Damian Wayne)?","o":["Batman","El Rey León","Harry Potter","Shrek"],"c":0,"e":"🎭"},{"q":"En Batman, ¿Robin (Damian Wayne) es un héroe/aliado o un villano?","o":["Es un lugar, no un personaje","No aparece en esa saga","Un villano","Un héroe o aliado"],"c":3,"e":"⚖️"},{"q":"¿En qué película o saga aparece Alfred Pennyworth?","o":["Shrek","Star Wars","Los Increíbles","Batman"],"c":3,"e":"🎬"},{"q":"¿A qué franquicia pertenece el personaje Alfred Pennyworth?","o":["Harry Potter","Spider-Man","Batman","Toy Story"],"c":2,"e":"🎭"},{"q":"En Batman, ¿Alfred Pennyworth es un héroe/aliado o un villano?","o":["Un villano","Un héroe o aliado","Es un lugar, no un personaje","No aparece en esa saga"],"c":1,"e":"⚖️"},{"q":"¿En qué película o saga aparece el Comisario Gordon?","o":["Los Increíbles","Spider-Man","Batman","Toy Story"],"c":2,"e":"🎬"},{"q":"¿A qué franquicia pertenece el personaje el Comisario Gordon?","o":["Batman","Los Increíbles","Star Wars","Toy Story"],"c":0,"e":"🎭"},{"q":"En Batman, ¿el Comisario Gordon es un héroe/aliado o un villano?","o":["No aparece en esa saga","Es un lugar, no un personaje","Un héroe o aliado","Un villano"],"c":2,"e":"⚖️"},{"q":"¿En qué película o saga aparece Batgirl (Barbara Gordon)?","o":["Star Wars","Toy Story","Batman","Harry Potter"],"c":2,"e":"🎬"},{"q":"¿A qué franquicia pertenece el personaje Batgirl (Barbara Gordon)?","o":["Spider-Man","Harry Potter","Batman","Los Increíbles"],"c":2,"e":"🎭"},{"q":"En Batman, ¿Batgirl (Barbara Gordon) es un héroe/aliado o un villano?","o":["Un villano","No aparece en esa saga","Un héroe o aliado","Es un lugar, no un personaje"],"c":2,"e":"⚖️"},{"q":"¿En qué película o saga aparece Nightwing?","o":["Star Wars","Spider-Man","Batman","Los Increíbles"],"c":2,"e":"🎬"},{"q":"¿A qué franquicia pertenece el personaje Nightwing?","o":["Batman","Los Increíbles","Star Wars","El Rey León"],"c":0,"e":"🎭"},{"q":"En Batman, ¿Nightwing es un héroe/aliado o un villano?","o":["No aparece en esa saga","Un héroe o aliado","Es un lugar, no un personaje","Un villano"],"c":1,"e":"⚖️"},{"q":"¿En qué película o saga aparece Red Hood?","o":["Batman","Toy Story","Los Increíbles","Star Wars"],"c":0,"e":"🎬"},{"q":"¿A qué franquicia pertenece el personaje Red Hood?","o":["Toy Story","Harry Potter","El Rey León","Batman"],"c":3,"e":"🎭"},{"q":"En Batman, ¿Red Hood es un héroe/aliado o un villano?","o":["Es un lugar, no un personaje","Un héroe o aliado","Un villano","No aparece en esa saga"],"c":1,"e":"⚖️"},{"q":"¿En qué película o saga aparece Lucius Fox?","o":["Star Wars","Batman","Harry Potter","Los Increíbles"],"c":1,"e":"🎬"},{"q":"¿A qué franquicia pertenece el personaje Lucius Fox?","o":["Toy Story","Batman","Spider-Man","Los Increíbles"],"c":1,"e":"🎭"},{"q":"En Batman, ¿Lucius Fox es un héroe/aliado o un villano?","o":["Un villano","No aparece en esa saga","Un héroe o aliado","Es un lugar, no un personaje"],"c":2,"e":"⚖️"},{"q":"¿En qué película o saga aparece Batwoman (Kate Kane)?","o":["Toy Story","Batman","Los Increíbles","El Rey León"],"c":1,"e":"🎬"},{"q":"¿A qué franquicia pertenece el personaje Batwoman (Kate Kane)?","o":["Batman","Toy Story","Spider-Man","Los Increíbles"],"c":0,"e":"🎭"},{"q":"En Batman, ¿Batwoman (Kate Kane) es un héroe/aliado o un villano?","o":["Un héroe o aliado","Es un lugar, no un personaje","No aparece en esa saga","Un villano"],"c":0,"e":"⚖️"},{"q":"¿En qué película o saga aparece la Cazadora (Huntress)?","o":["Spider-Man","Harry Potter","Shrek","Batman"],"c":3,"e":"🎬"},{"q":"¿A qué franquicia pertenece el personaje la Cazadora (Huntress)?","o":["Spider-Man","Batman","Toy Story","Harry Potter"],"c":1,"e":"🎭"},{"q":"En Batman, ¿la Cazadora (Huntress) es un héroe/aliado o un villano?","o":["Es un lugar, no un personaje","Un villano","No aparece en esa saga","Un héroe o aliado"],"c":3,"e":"⚖️"},{"q":"¿En qué película o saga aparece Azrael?","o":["Batman","Star Wars","Toy Story","Shrek"],"c":0,"e":"🎬"},{"q":"¿A qué franquicia pertenece el personaje Azrael?","o":["Shrek","Batman","Toy Story","Star Wars"],"c":1,"e":"🎭"},{"q":"En Batman, ¿Azrael es un héroe/aliado o un villano?","o":["Un héroe o aliado","Un villano","No aparece en esa saga","Es un lugar, no un personaje"],"c":1,"e":"⚖️"},{"q":"¿En qué película o saga aparece el Joker?","o":["Los Increíbles","Batman","Harry Potter","El Rey León"],"c":1,"e":"🎬"},{"q":"¿A qué franquicia pertenece el personaje el Joker?","o":["Los Increíbles","Spider-Man","Batman","El Rey León"],"c":2,"e":"🎭"},{"q":"En Batman, ¿el Joker es un héroe/aliado o un villano?","o":["Es un lugar, no un personaje","Un héroe o aliado","No aparece en esa saga","Un villano"],"c":3,"e":"⚖️"},{"q":"¿En qué película o saga aparece el Pingüino?","o":["Toy Story","Harry Potter","Los Increíbles","Batman"],"c":3,"e":"🎬"},{"q":"¿A qué franquicia pertenece el personaje el Pingüino?","o":["Spider-Man","Toy Story","Batman","Star Wars"],"c":2,"e":"🎭"},{"q":"En Batman, ¿el Pingüino es un héroe/aliado o un villano?","o":["No aparece en esa saga","Un villano","Un héroe o aliado","Es un lugar, no un personaje"],"c":1,"e":"⚖️"},{"q":"¿En qué película o saga aparece el Enigma?","o":["Batman","Spider-Man","Los Increíbles","Toy Story"],"c":0,"e":"🎬"},{"q":"¿A qué franquicia pertenece el personaje el Enigma?","o":["El Rey León","Batman","Spider-Man","Toy Story"],"c":1,"e":"🎭"},{"q":"En Batman, ¿el Enigma es un héroe/aliado o un villano?","o":["Un villano","Es un lugar, no un personaje","No aparece en esa saga","Un héroe o aliado"],"c":0,"e":"⚖️"},{"q":"¿En qué película o saga aparece Dos Caras?","o":["Star Wars","Batman","Harry Potter","El Rey León"],"c":1,"e":"🎬"},{"q":"¿A qué franquicia pertenece el personaje Dos Caras?","o":["Spider-Man","Shrek","Batman","Star Wars"],"c":2,"e":"🎭"},{"q":"En Batman, ¿Dos Caras es un héroe/aliado o un villano?","o":["No aparece en esa saga","Es un lugar, no un personaje","Un héroe o aliado","Un villano"],"c":3,"e":"⚖️"},{"q":"¿En qué película o saga aparece Bane?","o":["Toy Story","Star Wars","Batman","Shrek"],"c":2,"e":"🎬"},{"q":"¿A qué franquicia pertenece el personaje Bane?","o":["Los Increíbles","Star Wars","Batman","El Rey León"],"c":2,"e":"🎭"},{"q":"En Batman, ¿Bane es un héroe/aliado o un villano?","o":["Es un lugar, no un personaje","Un villano","Un héroe o aliado","No aparece en esa saga"],"c":1,"e":"⚖️"},{"q":"¿En qué película o saga aparece Hiedra Venenosa?","o":["Star Wars","Batman","Toy Story","Spider-Man"],"c":1,"e":"🎬"},{"q":"¿A qué franquicia pertenece el personaje Hiedra Venenosa?","o":["Spider-Man","Toy Story","Batman","Los Increíbles"],"c":2,"e":"🎭"},{"q":"En Batman, ¿Hiedra Venenosa es un héroe/aliado o un villano?","o":["Un héroe o aliado","Es un lugar, no un personaje","No aparece en esa saga","Un villano"],"c":3,"e":"⚖️"},{"q":"¿En qué película o saga aparece Gatúbela?","o":["Spider-Man","Batman","El Rey León","Harry Potter"],"c":1,"e":"🎬"},{"q":"¿A qué franquicia pertenece el personaje Gatúbela?","o":["Los Increíbles","Batman","Shrek","El Rey León"],"c":1,"e":"🎭"},{"q":"En Batman, ¿Gatúbela es un héroe/aliado o un villano?","o":["Es un lugar, no un personaje","Un villano","No aparece en esa saga","Un héroe o aliado"],"c":1,"e":"⚖️"},{"q":"¿En qué película o saga aparece Mr. Frío?","o":["Toy Story","Los Increíbles","Batman","El Rey León"],"c":2,"e":"🎬"},{"q":"¿A qué franquicia pertenece el personaje Mr. Frío?","o":["El Rey León","Batman","Toy Story","Star Wars"],"c":1,"e":"🎭"},{"q":"En Batman, ¿Mr. Frío es un héroe/aliado o un villano?","o":["Un villano","Es un lugar, no un personaje","Un héroe o aliado","No aparece en esa saga"],"c":0,"e":"⚖️"},{"q":"¿En qué película o saga aparece el Espantapájaros?","o":["Batman","El Rey León","Spider-Man","Harry Potter"],"c":0,"e":"🎬"},{"q":"¿A qué franquicia pertenece el personaje el Espantapájaros?","o":["Shrek","Batman","El Rey León","Star Wars"],"c":1,"e":"🎭"},{"q":"En Batman, ¿el Espantapájaros es un héroe/aliado o un villano?","o":["No aparece en esa saga","Es un lugar, no un personaje","Un héroe o aliado","Un villano"],"c":3,"e":"⚖️"},{"q":"¿En qué película o saga aparece Ra's al Ghul?","o":["Batman","El Rey León","Spider-Man","Harry Potter"],"c":0,"e":"🎬"},{"q":"¿A qué franquicia pertenece el personaje Ra's al Ghul?","o":["Shrek","Harry Potter","Batman","Toy Story"],"c":2,"e":"🎭"},{"q":"En Batman, ¿Ra's al Ghul es un héroe/aliado o un villano?","o":["No aparece en esa saga","Un héroe o aliado","Es un lugar, no un personaje","Un villano"],"c":3,"e":"⚖️"},{"q":"¿En qué película o saga aparece Harley Quinn?","o":["Spider-Man","Batman","Harry Potter","Star Wars"],"c":1,"e":"🎬"},{"q":"¿A qué franquicia pertenece el personaje Harley Quinn?","o":["Batman","Shrek","Los Increíbles","El Rey León"],"c":0,"e":"🎭"},{"q":"En Batman, ¿Harley Quinn es un héroe/aliado o un villano?","o":["Un villano","No aparece en esa saga","Es un lugar, no un personaje","Un héroe o aliado"],"c":0,"e":"⚖️"},{"q":"¿En qué película o saga aparece Killer Croc?","o":["El Rey León","Batman","Los Increíbles","Toy Story"],"c":1,"e":"🎬"},{"q":"¿A qué franquicia pertenece el personaje Killer Croc?","o":["Spider-Man","Shrek","Batman","Harry Potter"],"c":2,"e":"🎭"},{"q":"En Batman, ¿Killer Croc es un héroe/aliado o un villano?","o":["Es un lugar, no un personaje","No aparece en esa saga","Un villano","Un héroe o aliado"],"c":2,"e":"⚖️"},{"q":"¿En qué película o saga aparece Cara de Barro?","o":["Star Wars","Batman","Spider-Man","Harry Potter"],"c":1,"e":"🎬"},{"q":"¿A qué franquicia pertenece el personaje Cara de Barro?","o":["Spider-Man","Shrek","Harry Potter","Batman"],"c":3,"e":"🎭"},{"q":"En Batman, ¿Cara de Barro es un héroe/aliado o un villano?","o":["Un héroe o aliado","No aparece en esa saga","Es un lugar, no un personaje","Un villano"],"c":3,"e":"⚖️"},{"q":"¿En qué película o saga aparece el Sombrerero Loco?","o":["Batman","Spider-Man","Harry Potter","El Rey León"],"c":0,"e":"🎬"},{"q":"¿A qué franquicia pertenece el personaje el Sombrerero Loco?","o":["Spider-Man","El Rey León","Star Wars","Batman"],"c":3,"e":"🎭"},{"q":"En Batman, ¿el Sombrerero Loco es un héroe/aliado o un villano?","o":["Un villano","Es un lugar, no un personaje","No aparece en esa saga","Un héroe o aliado"],"c":0,"e":"⚖️"},{"q":"¿En qué película o saga aparece Máscara Negra?","o":["Star Wars","Toy Story","Batman","Spider-Man"],"c":2,"e":"🎬"},{"q":"¿A qué franquicia pertenece el personaje Máscara Negra?","o":["Los Increíbles","Star Wars","Toy Story","Batman"],"c":3,"e":"🎭"},{"q":"En Batman, ¿Máscara Negra es un héroe/aliado o un villano?","o":["Es un lugar, no un personaje","Un héroe o aliado","Un villano","No aparece en esa saga"],"c":2,"e":"⚖️"},{"q":"¿En qué película o saga aparece Talia al Ghul?","o":["Los Increíbles","Batman","El Rey León","Spider-Man"],"c":1,"e":"🎬"},{"q":"¿A qué franquicia pertenece el personaje Talia al Ghul?","o":["Harry Potter","Shrek","Batman","Star Wars"],"c":2,"e":"🎭"},{"q":"En Batman, ¿Talia al Ghul es un héroe/aliado o un villano?","o":["Un villano","Es un lugar, no un personaje","No aparece en esa saga","Un héroe o aliado"],"c":0,"e":"⚖️"},{"q":"¿En qué película o saga aparece Mr. Zsasz?","o":["Shrek","Harry Potter","Los Increíbles","Batman"],"c":3,"e":"🎬"},{"q":"¿A qué franquicia pertenece el personaje Mr. Zsasz?","o":["Spider-Man","Batman","Shrek","Harry Potter"],"c":1,"e":"🎭"},{"q":"En Batman, ¿Mr. Zsasz es un héroe/aliado o un villano?","o":["Un héroe o aliado","No aparece en esa saga","Es un lugar, no un personaje","Un villano"],"c":3,"e":"⚖️"},{"q":"¿En qué película o saga aparece Hush?","o":["Spider-Man","Batman","Star Wars","Los Increíbles"],"c":1,"e":"🎬"},{"q":"¿A qué franquicia pertenece el personaje Hush?","o":["Spider-Man","El Rey León","Batman","Harry Potter"],"c":2,"e":"🎭"},{"q":"En Batman, ¿Hush es un héroe/aliado o un villano?","o":["Es un lugar, no un personaje","Un héroe o aliado","Un villano","No aparece en esa saga"],"c":2,"e":"⚖️"},{"q":"¿En qué película o saga aparece Deadshot?","o":["Los Increíbles","Toy Story","Shrek","Batman"],"c":3,"e":"🎬"},{"q":"¿A qué franquicia pertenece el personaje Deadshot?","o":["Batman","Spider-Man","Star Wars","Shrek"],"c":0,"e":"🎭"},{"q":"En Batman, ¿Deadshot es un héroe/aliado o un villano?","o":["Un villano","No aparece en esa saga","Un héroe o aliado","Es un lugar, no un personaje"],"c":0,"e":"⚖️"},{"q":"¿Cuál de estos personajes es de Batman?","o":["Batman (Bruce Wayne)","Kitty Patas Suaves","Buzz Lightyear","Ben Reilly"],"c":0,"e":"🎭"},{"q":"¿A qué héroe se enfrenta Joker?","o":["Wolverine","Luke Skywalker","Superman","Batman"],"c":3,"e":"⚔️"},{"q":"¿De qué franquicia es el villano Joker?","o":["Star Wars","Batman","Toy Story","Spider-Man"],"c":1,"e":"😈"},{"q":"¿Es Joker un aliado o un enemigo de Batman?","o":["Un enemigo","El mismo héroe","Un aliado","Un familiar"],"c":0,"e":"😈"},{"q":"¿A qué héroe se enfrenta Pingüino?","o":["Spider-Man","Batman","Iron Man","Luke Skywalker"],"c":1,"e":"⚔️"},{"q":"¿De qué franquicia es el villano Pingüino?","o":["Batman","Star Wars","Los Increíbles","Shrek"],"c":0,"e":"😈"},{"q":"¿Es Pingüino un aliado o un enemigo de Batman?","o":["El mismo héroe","Un aliado","Un enemigo","Un familiar"],"c":2,"e":"😈"},{"q":"¿A qué héroe se enfrenta Enigma?","o":["Iron Man","Batman","Harry Potter","Spider-Man"],"c":1,"e":"⚔️"},{"q":"¿De qué franquicia es el villano Enigma?","o":["Spider-Man","Shrek","Toy Story","Batman"],"c":3,"e":"😈"},{"q":"¿Es Enigma un aliado o un enemigo de Batman?","o":["El mismo héroe","Un familiar","Un aliado","Un enemigo"],"c":3,"e":"😈"},{"q":"¿A qué héroe se enfrenta Dos Caras?","o":["Batman","Luke Skywalker","Harry Potter","Wolverine"],"c":0,"e":"⚔️"},{"q":"¿De qué franquicia es el villano Dos Caras?","o":["Batman","Harry Potter","El Rey León","Los Increíbles"],"c":0,"e":"😈"},{"q":"¿Es Dos Caras un aliado o un enemigo de Batman?","o":["Un aliado","El mismo héroe","Un familiar","Un enemigo"],"c":3,"e":"😈"},{"q":"¿A qué héroe se enfrenta Bane?","o":["Luke Skywalker","Batman","el Capitán América","Harry Potter"],"c":1,"e":"⚔️"},{"q":"¿De qué franquicia es el villano Bane?","o":["Harry Potter","Toy Story","Batman","Shrek"],"c":2,"e":"😈"},{"q":"¿Es Bane un aliado o un enemigo de Batman?","o":["Un familiar","Un enemigo","Un aliado","El mismo héroe"],"c":1,"e":"😈"},{"q":"¿A qué héroe se enfrenta Hiedra Venenosa?","o":["Batman","Shrek","Iron Man","Luke Skywalker"],"c":0,"e":"⚔️"},{"q":"¿De qué franquicia es el villano Hiedra Venenosa?","o":["Batman","Spider-Man","Toy Story","Shrek"],"c":0,"e":"😈"},{"q":"¿Es Hiedra Venenosa un aliado o un enemigo de Batman?","o":["Un enemigo","Un familiar","El mismo héroe","Un aliado"],"c":0,"e":"😈"},{"q":"¿A qué héroe se enfrenta Gatúbela?","o":["el Capitán América","Batman","Luke Skywalker","Harry Potter"],"c":1,"e":"⚔️"},{"q":"¿De qué franquicia es el villano Gatúbela?","o":["Batman","Spider-Man","Harry Potter","Star Wars"],"c":0,"e":"😈"},{"q":"¿Es Gatúbela un aliado o un enemigo de Batman?","o":["Un familiar","El mismo héroe","Un aliado","Un enemigo"],"c":3,"e":"😈"},{"q":"¿A qué héroe se enfrenta Mr. Frío?","o":["Luke Skywalker","Wolverine","Batman","Shrek"],"c":2,"e":"⚔️"},{"q":"¿De qué franquicia es el villano Mr. Frío?","o":["Harry Potter","Star Wars","El Rey León","Batman"],"c":3,"e":"😈"},{"q":"¿Es Mr. Frío un aliado o un enemigo de Batman?","o":["El mismo héroe","Un enemigo","Un aliado","Un familiar"],"c":1,"e":"😈"},{"q":"¿A qué héroe se enfrenta Espantapájaros?","o":["Batman","Harry Potter","Shrek","Superman"],"c":0,"e":"⚔️"},{"q":"¿De qué franquicia es el villano Espantapájaros?","o":["Spider-Man","Batman","Shrek","Toy Story"],"c":1,"e":"😈"},{"q":"¿Es Espantapájaros un aliado o un enemigo de Batman?","o":["Un enemigo","Un aliado","Un familiar","El mismo héroe"],"c":0,"e":"😈"},{"q":"¿A qué héroe se enfrenta Ra's al Ghul?","o":["Batman","Shrek","el Capitán América","Wolverine"],"c":0,"e":"⚔️"},{"q":"¿De qué franquicia es el villano Ra's al Ghul?","o":["Batman","Los Increíbles","Toy Story","Star Wars"],"c":0,"e":"😈"},{"q":"¿Es Ra's al Ghul un aliado o un enemigo de Batman?","o":["Un enemigo","El mismo héroe","Un aliado","Un familiar"],"c":0,"e":"😈"},{"q":"¿A qué héroe se enfrenta Harley Quinn?","o":["Wolverine","Batman","Shrek","el Capitán América"],"c":1,"e":"⚔️"},{"q":"¿De qué franquicia es el villano Harley Quinn?","o":["Toy Story","Batman","Harry Potter","Star Wars"],"c":1,"e":"😈"},{"q":"¿Es Harley Quinn un aliado o un enemigo de Batman?","o":["Un familiar","Un aliado","El mismo héroe","Un enemigo"],"c":3,"e":"😈"},{"q":"¿A qué héroe se enfrenta Killer Croc?","o":["Superman","Batman","Wolverine","el Capitán América"],"c":1,"e":"⚔️"},{"q":"¿De qué franquicia es el villano Killer Croc?","o":["Batman","Star Wars","Shrek","Toy Story"],"c":0,"e":"😈"},{"q":"¿Es Killer Croc un aliado o un enemigo de Batman?","o":["El mismo héroe","Un aliado","Un familiar","Un enemigo"],"c":3,"e":"😈"},{"q":"¿A qué héroe se enfrenta Cara de Barro?","o":["Batman","Luke Skywalker","el Capitán América","Iron Man"],"c":0,"e":"⚔️"},{"q":"¿De qué franquicia es el villano Cara de Barro?","o":["Los Increíbles","Batman","Shrek","Toy Story"],"c":1,"e":"😈"},{"q":"¿Es Cara de Barro un aliado o un enemigo de Batman?","o":["Un enemigo","El mismo héroe","Un familiar","Un aliado"],"c":0,"e":"😈"},{"q":"¿A qué héroe se enfrenta Sombrerero Loco?","o":["Batman","Spider-Man","Luke Skywalker","Wolverine"],"c":0,"e":"⚔️"},{"q":"¿De qué franquicia es el villano Sombrerero Loco?","o":["Batman","Harry Potter","El Rey León","Toy Story"],"c":0,"e":"😈"},{"q":"¿Es Sombrerero Loco un aliado o un enemigo de Batman?","o":["Un familiar","Un aliado","Un enemigo","El mismo héroe"],"c":2,"e":"😈"},{"q":"¿A qué héroe se enfrenta Hombre Murciélago?","o":["Luke Skywalker","Shrek","Harry Potter","Batman"],"c":3,"e":"⚔️"},{"q":"¿De qué franquicia es el villano Hombre Murciélago?","o":["Toy Story","Shrek","El Rey León","Batman"],"c":3,"e":"😈"},{"q":"¿Es Hombre Murciélago un aliado o un enemigo de Batman?","o":["Un familiar","Un aliado","El mismo héroe","Un enemigo"],"c":3,"e":"😈"},{"q":"¿A qué héroe se enfrenta Deadshot?","o":["el Capitán América","Batman","Spider-Man","Wolverine"],"c":1,"e":"⚔️"},{"q":"¿De qué franquicia es el villano Deadshot?","o":["Shrek","Spider-Man","Los Increíbles","Batman"],"c":3,"e":"😈"},{"q":"¿Es Deadshot un aliado o un enemigo de Batman?","o":["Un aliado","Un enemigo","El mismo héroe","Un familiar"],"c":1,"e":"😈"},{"q":"¿A qué héroe se enfrenta Máscara Negra?","o":["Luke Skywalker","el Capitán América","Batman","Shrek"],"c":2,"e":"⚔️"},{"q":"¿De qué franquicia es el villano Máscara Negra?","o":["Los Increíbles","Batman","Shrek","Spider-Man"],"c":1,"e":"😈"},{"q":"¿Es Máscara Negra un aliado o un enemigo de Batman?","o":["El mismo héroe","Un familiar","Un enemigo","Un aliado"],"c":2,"e":"😈"},{"q":"¿A qué héroe se enfrenta Firefly?","o":["Iron Man","Batman","Superman","Spider-Man"],"c":1,"e":"⚔️"},{"q":"¿De qué franquicia es el villano Firefly?","o":["Batman","Toy Story","Star Wars","Los Increíbles"],"c":0,"e":"😈"},{"q":"¿Es Firefly un aliado o un enemigo de Batman?","o":["Un familiar","Un enemigo","Un aliado","El mismo héroe"],"c":1,"e":"😈"},{"q":"¿A qué héroe se enfrenta Muñeco (Ventrílocuo)?","o":["Superman","Batman","Wolverine","Iron Man"],"c":1,"e":"⚔️"},{"q":"¿De qué franquicia es el villano Muñeco (Ventrílocuo)?","o":["Harry Potter","Toy Story","Shrek","Batman"],"c":3,"e":"😈"},{"q":"¿Es Muñeco (Ventrílocuo) un aliado o un enemigo de Batman?","o":["Un enemigo","Un aliado","Un familiar","El mismo héroe"],"c":0,"e":"😈"},{"q":"¿A qué héroe se enfrenta Hush?","o":["Spider-Man","Harry Potter","Wolverine","Batman"],"c":3,"e":"⚔️"},{"q":"¿De qué franquicia es el villano Hush?","o":["Star Wars","Batman","El Rey León","Spider-Man"],"c":1,"e":"😈"},{"q":"¿Es Hush un aliado o un enemigo de Batman?","o":["Un enemigo","El mismo héroe","Un familiar","Un aliado"],"c":0,"e":"😈"}]}