{"cat":"dragonball","name":"Dragón Ball","emoji":"🐉","questions":[{"q":"¿Cuál es el nombre del protagonista de Dragon Ball?","o":["Vegeta","Goku","Piccolo","Krillin"],"c":1,"e":"🥋"},{"q":"¿Cómo se llama el planeta natal de la raza Saiyan de Goku?","o":["Namek","Vegeta","Kaio-shin","Freezer"],"c":1,"e":"💥"},{"q":"¿Cuántas esferas del dragón existen para invocar a Shenlong?","o":["Cinco","Seis","Siete","Ocho"],"c":2,"e":"⭐"},{"q":"¿Cómo se llama el hijo mayor de Goku?","o":["Goten","Gohan","Trunks","Pan"],"c":1,"e":"👦"},{"q":"¿Cómo se llama el villano que destruye el planeta Namek buscando la inmortalidad?","o":["Cell","Buu","Freezer","Broly"],"c":2,"e":"❄️"},{"q":"¿Cómo se llama la técnica icónica de Goku donde concentra energía entre sus manos?","o":["Kamehameha","Genkidama","Kaioken","Makankosappo"],"c":0,"e":"🌊"},{"q":"¿Quién es el príncipe saiyajin, rival y luego aliado de Goku?","o":["Broly","Vegeta","Raditz","Nappa"],"c":1,"e":"👑"},{"q":"¿Quién entrenó a Goku y Krilin cuando eran niños?","o":["El Maestro Roshi","Kaio-sama","Mr. Popo","Karin"],"c":0,"e":"🐢"},{"q":"¿Cómo se llama el mejor amigo bajito y sin nariz de Goku?","o":["Yamcha","Ten Shin Han","Krilin","Chaoz"],"c":2,"e":"🧡"},{"q":"¿Qué androide 'perfecto' absorbe a los androides 17 y 18?","o":["Cell","Freezer","Buu","Dr. Gero"],"c":0,"e":"🦗"},{"q":"¿Cómo se llama el dragón que cumple deseos con las esferas?","o":["Porunga","Shenlong","Icarus","Karin"],"c":1,"e":"🐉"},{"q":"¿Qué namekiano fue villano y luego mentor de Gohan?","o":["Dendé","Nail","Piccolo","Kami-sama"],"c":2,"e":"🟢"},{"q":"¿Cómo se llama la transformación de cabello dorado de los saiyajin?","o":["Ultra Instinto","Super Saiyajin","Kaio-ken","Modo Dios"],"c":1,"e":"⚡"},{"q":"¿Cómo se llama la esposa de Goku?","o":["Bulma","Milk (Chi-Chi)","Videl","N.º 18"],"c":1,"e":"❤️"},{"q":"¿Qué villano rosado y regordete amenaza la Tierra en la saga final de Z?","o":["Majin Buu","Cell","Garlick Jr.","Dabura"],"c":0,"e":"🍬"},{"q":"¿Cómo se llama el hijo de Vegeta y Bulma?","o":["Goten","Trunks","Broly","Bardock"],"c":1,"e":"⚔️"},{"q":"¿Quién es la científica amiga de Goku desde el primer capítulo?","o":["Launch","Videl","Bulma","N.º 18"],"c":2,"e":"🔧"},{"q":"¿Cómo se llama el torneo de peleas más famoso de la serie?","o":["Torneo del Poder","Torneo de las Artes Marciales","Copa Saiyajin","Liga Namek"],"c":1,"e":"🥋"}]}